<?xml version="1.0" encoding="UTF-8" standalone="no"?>
<sfObject creatable="true" deleteable="true" detailsLoaded="false" editPermission="false" keyPrefix="a7X" label="Product Associated Services" labelPlural="soprodsvcs" layoutable="true" n="rstk__soprodsvc__c" queryable="true" readPermission="false" retrieveable="true" s="" t="Product Associated Services (a7X)" updatable="true">
  <standardActions>
    <sfActionLink modes="ObjectHome rstk__soprodsvcs2__r rstk__soprodsvcs__r" n="New"/>
    <sfActionLink modes="View rstk__soprodsvcs2__r rstk__soprodsvcs__r" n="Edit" requiresRow="true" s="2"/>
    <sfActionLink modes="View rstk__soprodsvcs2__r rstk__soprodsvcs__r" n="Delete" requiresRow="true" s="3"/>
    <sfActionLink lightningActionName="MassChangeOwner" massAction="true" modes="View List all_related_lists" n="ChangeOwnerOne" t="Change Owner"/>
    <sfActionLink modes="View rstk__soprodsvcs2__r rstk__soprodsvcs__r" n="ShowMore" t="Show More"/>
    <sfActionLink modes="View rstk__soprodsvcs2__r rstk__soprodsvcs__r" n="GoToList" t="Go To List"/>
    <sfActionLink modes="RelatedList" n="PrevPage" t="Previous Page"/>
    <sfActionLink modes="RelatedList" n="NextPage" t="Next Page"/>
  </standardActions>
</sfObject>
